{
	"animations": [
		{
			"offsets": [
				-2,
				0
			],
			"loop": false,
			"fps": 24,
			"anim": "idle",
			"indices": [],
			"name": "IDLE"
		},
		{
			"offsets": [
				-2,
				-6
			],
			"loop": false,
			"fps": 24,
			"anim": "singLEFT",
			"indices": [],
			"name": "LEFT"
		},
		{
			"offsets": [
				0,
				10
			],
			"loop": false,
			"fps": 24,
			"anim": "singDOWN",
			"indices": [],
			"name": "DOWN"
		},
		{
			"offsets": [
				-2,
				16
			],
			"loop": false,
			"fps": 24,
			"anim": "singUP",
			"indices": [],
			"name": "UP"
		},
		{
			"offsets": [
				-3,
				20
			],
			"loop": false,
			"fps": 24,
			"anim": "singRIGHT",
			"indices": [],
			"name": "RIGHT"
		},
		{
			"offsets": [
				0,
				-3
			],
			"loop": false,
			"fps": 24,
			"anim": "sigh",
			"indices": [],
			"name": "SIGH"
		}
	],
	"no_antialiasing": false,
	"image": "characters/Asuka",
	"position": [
		40,
		-180
	],
	"healthicon": "asuka",
	"flip_x": false,
	"healthbar_colors": [
		227,
		98,
		86
	],
	"camera_position": [
		-820,
		-150
	],
	"sing_duration": 6.1,
	"scale": 1.3
}